__init__.py
entity.py
homeassistant_sdk.py
homeassistant_sdk-0.0.3.dist-info/METADATA
homeassistant_sdk-0.0.3.dist-info/WHEEL
homeassistant_sdk-0.0.3.dist-info/top_level.txt
homeassistant_sdk-0.0.3.dist-info/RECORD
