Metadata-Version: 2.1
Name: homeassistant-sdk
Version: 0.0.3
Summary: homeassistant websocket sdk api client
Author-email: alanwoods <elanworld@163.com>
Project-URL: Homepage, https://github.com/elanworld/homeassistant-sdk
Project-URL: Bug Tracker, https://github.com/elanworld/homeassistant-sdk/issues
Classifier: Programming Language :: Python :: 3
Classifier: License :: OSI Approved :: MIT License
Classifier: Operating System :: OS Independent
Requires-Python: >=3.6
